Metadata-Version: 2.1
Name: odoo-addon-stock_request_kanban
Version: 18.0.1.0.1.2
Requires-Python: >=3.10
Requires-Dist: odoo-addon-stock_request==18.0.*
Requires-Dist: odoo==18.0.*
Summary: Adds a stock request order, and takes stock requests as lines
Home-page: https://github.com/OCA/stock-logistics-request
License: LGPL-3
Author: Creu Blanca, ForgeFlow, Odoo Community Association (OCA)
Author-email: support@odoo-community.org
Classifier: Programming Language :: Python
Classifier: Framework :: Odoo
Classifier: Framework :: Odoo :: 18.0
Classifier: License :: OSI Approved :: GNU Lesser General Public License v3 (LGPLv3)
